swarms_memory/__init__.py
swarms_memory/dbs/__init__.py
swarms_memory/dbs/base_db.py
swarms_memory/dbs/pg.py
swarms_memory/dbs/sqlite.py
swarms_memory/embeddings/__init__.py
swarms_memory/embeddings/embedding_utils.py
swarms_memory/embeddings/litellm_embeddings.py
swarms_memory/utils/__init__.py
swarms_memory/utils/action_subtask.py
swarms_memory/utils/dict_internal_memory.py
swarms_memory/utils/dict_shared_memory.py
swarms_memory/utils/short_term_memory.py
swarms_memory/utils/visual_memory.py
swarms_memory/vector_dbs/__init__.py
swarms_memory/vector_dbs/base_vectordb.py
swarms_memory/vector_dbs/chroma_db_wrapper.py
swarms_memory/vector_dbs/faiss_wrapper.py
swarms_memory/vector_dbs/pinecone_wrapper.py
swarms_memory/vector_dbs/qdrant_wrapper.py
swarms_memory/vector_dbs/singlestore_wrapper.py
swarms_memory/vector_dbs/zyphra_rag.py
swarms_memory-0.1.3.dist-info/LICENSE
swarms_memory-0.1.3.dist-info/METADATA
swarms_memory-0.1.3.dist-info/WHEEL
swarms_memory-0.1.3.dist-info/RECORD
