Metadata-Version: 2.3
Name: swarms-memory
Version: 0.1.3
Summary: Swarms Memory - Pytorch
License: MIT
Keywords: artificial intelligence,deep learning,optimizers,Prompt Engineering
Author: Kye Gomez
Author-email: kye@apac.ai
Requires-Python: >=3.10,<4.0
Classifier: Development Status :: 4 - Beta
Classifier: Intended Audience :: Developers
Classifier: License :: OSI Approved :: MIT License
Classifier: Programming Language :: Python :: 3
Classifier: Programming Language :: Python :: 3.10
Classifier: Programming Language :: Python :: 3.11
Classifier: Programming Language :: Python :: 3.12
Classifier: Programming Language :: Python :: 3.13
Classifier: Programming Language :: Python :: 3.9
Classifier: Topic :: Scientific/Engineering :: Artificial Intelligence
Requires-Dist: chromadb
Requires-Dist: faiss-cpu
Requires-Dist: fastembed
Requires-Dist: loguru
Requires-Dist: pinecone
Requires-Dist: pydantic
Requires-Dist: qdrant-client
Requires-Dist: sentence-transformers
Requires-Dist: singlestoredb
Requires-Dist: sqlalchemy
Requires-Dist: torch
Project-URL: Documentation, https://github.com/kyegomez/swarms-memory
Project-URL: Homepage, https://github.com/kyegomez/swarms-memory
Project-URL: Repository, https://github.com/kyegomez/swarms-memory
